minerva/__init__.py
minerva/analysis/__init__.py
minerva/analysis/complexity_performance_analysis.py
minerva/analysis/model_analysis.py
minerva/analysis/metrics/__init__.py
minerva/analysis/metrics/balanced_accuracy.py
minerva/analysis/metrics/pixel_accuracy.py
minerva/callback/embedding_logger_callback.py
minerva/data/__init__.py
minerva/data/data_module_tools.py
minerva/data/data_modules/__init__.py
minerva/data/data_modules/base.py
minerva/data/datasets/__init__.py
minerva/data/datasets/base.py
minerva/data/readers/__init__.py
minerva/data/readers/base_file_iterator.py
minerva/data/readers/csv_reader.py
minerva/data/readers/index_reader.py
minerva/data/readers/mdio_reader.py
minerva/data/readers/multi_reader.py
minerva/data/readers/patched_array_reader.py
minerva/data/readers/png_reader.py
minerva/data/readers/reader.py
minerva/data/readers/tabular_reader.py
minerva/data/readers/tiff_reader.py
minerva/data/readers/zarr_reader.py
minerva/engines/engine.py
minerva/engines/patch_inferencer_engine.py
minerva/losses/__init__.py
minerva/losses/_functional.py
minerva/losses/batchwise_barlowtwins_loss.py
minerva/losses/dice.py
minerva/losses/negative_cossine_similatiry.py
minerva/losses/ntxent_loss_poly.py
minerva/losses/topological_loss.py
minerva/losses/xtent_loss.py
minerva/models/__init__.py
minerva/models/adapters.py
minerva/models/finetune_adapters.py
minerva/models/loaders.py
minerva/models/nets/__init__.py
minerva/models/nets/base.py
minerva/models/nets/classic_ml_pipeline.py
minerva/models/nets/conv_autoencoders_encoders.py
minerva/models/nets/cpc_networks.py
minerva/models/nets/dcnn.py
minerva/models/nets/mlp.py
minerva/models/nets/siamese_network_wrapper.py
minerva/models/nets/tfc.py
minerva/models/nets/tnc.py
minerva/models/nets/image/deeplabv3.py
minerva/models/nets/image/setr.py
minerva/models/nets/image/unet.py
minerva/models/nets/image/vit.py
minerva/models/nets/image/wisenet.py
minerva/models/nets/time_series/cnns.py
minerva_ml-0.3.7b0.dist-info/licenses/LICENSE
minerva_ml-0.3.7b0.dist-info/METADATA
minerva_ml-0.3.7b0.dist-info/WHEEL
minerva_ml-0.3.7b0.dist-info/top_level.txt
minerva_ml-0.3.7b0.dist-info/RECORD
