Metadata-Version: 2.4
Name: minerva-ml
Version: 0.3.7b0
Summary: A framework for training machine learning models for researchers.
Author-email: Gabriel Gutierrez <gabriel.bgs00@gmail.com>, Otávio Napoli <otavio.napoli@ic.unicamp.br>, Fernando Gubitoso Marques <fernandogubitosom@gmail.com>, Edson Borin <borin@unicamp.br>
License: MIT License
Project-URL: Bug Tracker, https://github.com/discovery-unicamp/Minerva/issues
Project-URL: Homepage, https://github.com/discovery-unicamp/Minerva
Keywords: Deep Learning,Machine Learning,Pytorch,Research,Self-Supervised Learning,SSL
Classifier: License :: OSI Approved :: MIT License
Classifier: Programming Language :: Python
Classifier: Programming Language :: Python :: 3
Classifier: Development Status :: 4 - Beta
Classifier: Intended Audience :: Science/Research
Classifier: Operating System :: OS Independent
Classifier: Topic :: Scientific/Engineering :: Artificial Intelligence
Requires-Python: >=3.10
License-File: LICENSE
Requires-Dist: gitpython>=3
Requires-Dist: jsonargparse==4.37.0
Requires-Dist: lightning>=2.1.9
Requires-Dist: matplotlib>=3.7
Requires-Dist: numpy>=1.23.5
Requires-Dist: opencv-python>=4.10.0.84
Requires-Dist: pandas>=2.2.2
Requires-Dist: perlin-noise>=1.12
Requires-Dist: plotly>=5.18
Requires-Dist: PyYAML>=6.0
Requires-Dist: rich>=13.0
Requires-Dist: scikit-learn>=1.2.0
Requires-Dist: scipy>=1.10
Requires-Dist: statsmodels>=0.13
Requires-Dist: tifffile>=2024
Requires-Dist: timm>=1.0.2
Requires-Dist: torch>=2.0
Requires-Dist: torchinfo>=1.8.0
Requires-Dist: torchmetrics>=1.3.0
Requires-Dist: torchvision>=0.15
Requires-Dist: wrapt>=1.16
Requires-Dist: zarr>=2.17
Provides-Extra: dev
Requires-Dist: black; extra == "dev"
Requires-Dist: flake8; extra == "dev"
Requires-Dist: interrogate; extra == "dev"
Requires-Dist: ipykernel; extra == "dev"
Requires-Dist: mock; extra == "dev"
Requires-Dist: nbformat; extra == "dev"
Requires-Dist: pytest-coverage; extra == "dev"
Provides-Extra: docs
Requires-Dist: Ipython; extra == "docs"
Requires-Dist: myst-parser; extra == "docs"
Requires-Dist: nbsphinx; extra == "docs"
Requires-Dist: pandoc; extra == "docs"
Requires-Dist: sphinx-argparse; extra == "docs"
Requires-Dist: sphinx-autoapi; extra == "docs"
Requires-Dist: sphinx-autodoc-typehints; extra == "docs"
Requires-Dist: sphinx-rtd-theme; extra == "docs"
Requires-Dist: sphinx; extra == "docs"
Provides-Extra: analysis
Requires-Dist: codecarbon>=2.8.3; extra == "analysis"
Requires-Dist: ultralytics-thop>=2.0.14; extra == "analysis"
Dynamic: license-file
